metano/__init__.py
metano/check_all_transporters.py
metano/compute_rea_enthalpies.py
metano/constrain_rea_directions.py
metano/cycleanalysis.py
metano/deadends.py
metano/defines.py
metano/fba.py
metano/fva.py
metano/knockout.py
metano/linconstraints.py
metano/linearproblem.py
metano/metabolicflux.py
metano/metabolicmap.py
metano/metabolicmodel.py
metano/mfba.py
metano/mfm.py
metano/modelassert.py
metano/moma.py
metano/momaproblem.py
metano/moment.py
metano/nonlinearproblem.py
metano/objectivefun.py
metano/paramparser.py
metano/quadraticproblem.py
metano/reactionparser.py
metano/sbmlparser.py
metano/sbmlstructure.py
metano/sbmlwriter.py
metano/splitratios.py
metano/startpointiterator.py
metano/to_check_constraints.py
metano/to_classify_reactions.py
metano/to_diff_solutions.py
metano/to_evaluate_objective.py
metano/to_explicitbounds.py
metano/to_fix_names.py
metano/to_list_active_metab.py
metano/to_list_metab_names.py
metano/to_rea2m.py
metano/to_scatterplot.py
metano/transporterparser.py
metano/example/fba.sh
metano/example/fba_sulfolobus.txt
metano/example/mFBA_matrix.txt
metano/example/mFBA_raw.txt
metano/example/mfba.sh
metano/example/rea_sulfolobus.txt
metano/example/scatterplot.ini
metano/example/sce_sulfolobus.txt
metano-1.3.1.dist-info/LICENSE
metano-1.3.1.dist-info/METADATA
metano-1.3.1.dist-info/WHEEL
metano-1.3.1.dist-info/entry_points.txt
metano-1.3.1.dist-info/top_level.txt
metano-1.3.1.dist-info/RECORD
