Metadata-Version: 2.1
Name: metano
Version: 1.3.1
Summary: metano - A Toolkit for Metabolic Network Analysis and Optimization
Home-page: https://mmtb.brenda-enzymes.org/metano
Author: Julia Koblitz and Alexander Riemer
Author-email: julia.koblitz@dsmz.de
License: GPL
Keywords: genome-scale metabolic models flux balance analysis fba
Platform: UNKNOWN
Classifier: License :: OSI Approved :: GNU General Public License (GPL)
Classifier: Programming Language :: Python :: 3
Classifier: Development Status :: 5 - Production/Stable
Classifier: Intended Audience :: Science/Research
Classifier: Topic :: Scientific/Engineering :: Bio-Informatics
License-File: LICENSE
Requires-Dist: numpy
Requires-Dist: swiglpk
Requires-Dist: pymprog (>=1.0)
Requires-Dist: ecos
Requires-Dist: scipy
Requires-Dist: openopt
Requires-Dist: cvxpy
Requires-Dist: cvxopt
